biascheck/__init__.py
biascheck/analysis/__init__.py
biascheck/analysis/basecheck.py
biascheck/analysis/docucheck.py
biascheck/analysis/moducheck.py
biascheck/analysis/ragcheck.py
biascheck/analysis/setcheck.py
biascheck/utils/__init__.py
biascheck/utils/config.py
biascheck/utils/embed_utils.py
biascheck/utils/env_config.py
biascheck/utils/faiss_utils.py
biascheck/utils/lazy_imports.py
biascheck/utils/terms_loader.py
biascheck/visualisation/__init__.py
biascheck/visualisation/visualiser.py
biascheck-0.8.10.dist-info/LICENSE
biascheck-0.8.10.dist-info/METADATA
biascheck-0.8.10.dist-info/WHEEL
biascheck-0.8.10.dist-info/entry_points.txt
biascheck-0.8.10.dist-info/RECORD
