Metadata-Version: 2.3
Name: biascheck
Version: 0.8.10
Summary: A library for detecting and analyzing bias in text, datasets, and language models.
Author: Arjun Balaji
Requires-Python: >=3.9,<3.11
Classifier: Programming Language :: Python :: 3
Classifier: Programming Language :: Python :: 3.9
Classifier: Programming Language :: Python :: 3.10
Provides-Extra: all
Provides-Extra: gpu
Provides-Extra: test
Requires-Dist: PyMuPDF (>=1.21.0,<2.0.0)
Requires-Dist: PyPDF2 (>=3.0.0,<4.0.0)
Requires-Dist: datasets (>=2.12.0,<3.0.0)
Requires-Dist: faiss-gpu (>=1.7.0,<2.0.0) ; (sys_platform != "win32") and (extra == "gpu" or extra == "all")
Requires-Dist: langchain (>=0.1.0,<0.2.0)
Requires-Dist: langchain-community (>=0.0.20,<0.1.0)
Requires-Dist: langchain-core (>=0.1.0,<0.2.0)
Requires-Dist: langchain-huggingface (>=0.0.1,<0.1.0)
Requires-Dist: matplotlib (>=3.5.0,<4.0.0)
Requires-Dist: nltk (>=3.8.1,<4.0.0)
Requires-Dist: numpy (>=1.21.0,<2.0.0)
Requires-Dist: pandas (>=1.3.0,<2.0.0)
Requires-Dist: py2neo (>=2021.2.3,<2022.0.0)
Requires-Dist: pytest (>=7.0.0,<8.0.0) ; extra == "test" or extra == "all"
Requires-Dist: pytest-cov (>=4.0.0,<5.0.0) ; extra == "test" or extra == "all"
Requires-Dist: scikit-learn (>=1.0.0,<2.0.0)
Requires-Dist: scipy (>=1.7.0,<2.0.0)
Requires-Dist: seaborn (>=0.11.0,<0.12.0)
Requires-Dist: sentence-transformers (>=2.2.0,<3.0.0)
Requires-Dist: spacy (>=3.5.0,<4.0.0)
Requires-Dist: textblob (>=0.15.3,<0.16.0)
Requires-Dist: torch (>=2.0.0,<3.0.0) ; extra == "gpu" or extra == "all"
Requires-Dist: transformers (>=4.30.0,<5.0.0)
Requires-Dist: wordcloud (>=1.8.0,<2.0.0)
